MANIFEST.in
README.rst
docs.requirements.txt
inference.requirements.txt
requirements.txt
setup.cfg
setup.py
version.txt
zodb.requirements.txt
YAROM.egg-info/PKG-INFO
YAROM.egg-info/SOURCES.txt
YAROM.egg-info/dependency_links.txt
YAROM.egg-info/not-zip-safe
YAROM.egg-info/requires.txt
YAROM.egg-info/top_level.txt
yarom/__init__.py
yarom/classRegistry.py
yarom/configure.py
yarom/data.py
yarom/dataObject.py
yarom/dataUser.py
yarom/default.conf
yarom/deprecation.py
yarom/go_modifiers.py
yarom/graphObject.py
yarom/mappedClass.py
yarom/mappedProperty.py
yarom/mapper.py
yarom/mapperTypeResolver.py
yarom/mapperUtils.py
yarom/objectCollection.py
yarom/propertyMixins.py
yarom/propertyValue.py
yarom/quantity.py
yarom/rangedObjects.py
yarom/rdfTypeResolver.py
yarom/rdfUtils.py
yarom/relationship.py
yarom/rules.n3
yarom/simpleProperty.py
yarom/sleepycat.py
yarom/utils.py
yarom/variable.py
yarom/yProperty.py
yarom/zodb.py