Metadata-Version: 2.1
Name: YAROM
Version: 0.11.0.post20190612015311
Summary: Yet Another RDF-Object Mapper
Home-page: http://yarom.readthedocs.org/en/latest/
Author: Mark Watts
Author-email: wattsmark2015@gmail.com
License: BSD 3-clause
Download-URL: https://github.com/mwatts15/YAROM/archive/v0.11.0.post20190612015311.tar.gz
Platform: UNKNOWN
Classifier: Intended Audience :: Science/Research
Classifier: License :: OSI Approved :: BSD License
Classifier: Natural Language :: English
Classifier: Operating System :: OS Independent
Classifier: Programming Language :: Python :: 2.7
Classifier: Programming Language :: Python :: 3.3
Classifier: Programming Language :: Python :: 3.4
Classifier: Topic :: Scientific/Engineering
Provides-Extra: inference
Provides-Extra: docs
Provides-Extra: zodb
